LICENSE
MANIFEST.in
README.md
requirements.txt
setup.cfg
setup.py
ckanext/__init__.py
ckanext/multiuploader/__init__.py
ckanext/multiuploader/controllers.py
ckanext/multiuploader/lib.py
ckanext/multiuploader/plugin.py
ckanext/multiuploader/public/statics/drag_drop.js
ckanext/multiuploader/public/statics/multi_uploader.css
ckanext/multiuploader/public/statics/multi_uploader.js
ckanext/multiuploader/templates/package/new_resource.html
ckanext/multiuploader/templates/package/new_resource_not_draft.html
ckanext/multiuploader/templates/snippets/new_resource_form.html
ckanext/multiuploader/templates/snippets/progress_bar_modal.html
ckanext/multiuploader/tests/__init__.py
ckanext/multiuploader/tests/test_multiuploader.py
ckanext_multiuploader.egg-info/PKG-INFO
ckanext_multiuploader.egg-info/SOURCES.txt
ckanext_multiuploader.egg-info/dependency_links.txt
ckanext_multiuploader.egg-info/entry_points.txt
ckanext_multiuploader.egg-info/namespace_packages.txt
ckanext_multiuploader.egg-info/top_level.txt