Metadata-Version: 2.1
Name: ckanext-multiuploader
Version: 1.5.0
Summary: This CKAN extension helps users to upload multiple resources at once with drag&drop.
Home-page: https://github.com/TIBHannover/ckanext-multiuploader
Author: Pooya Oladazimi, Technische Informationsbibliothek(TIB)
Author-email: pooya.oladazimi@tib.eu
License: AGPL
Keywords: CKAN
Platform: UNKNOWN
Classifier: Development Status :: 3 - Alpha
Classifier: License :: OSI Approved :: GNU Affero General Public License v3 or later (AGPLv3+)
Classifier: Programming Language :: Python :: 3
